logspace/__init__.py
logspace-0.0.1.dist-info/LICENSE
logspace-0.0.1.dist-info/METADATA
logspace-0.0.1.dist-info/WHEEL
logspace-0.0.1.dist-info/top_level.txt
logspace-0.0.1.dist-info/RECORD
